MANIFEST.in
README.rst
setup.py
Crabsnack.egg-info/PKG-INFO
Crabsnack.egg-info/SOURCES.txt
Crabsnack.egg-info/dependency_links.txt
Crabsnack.egg-info/not-zip-safe
Crabsnack.egg-info/requires.txt
Crabsnack.egg-info/top_level.txt
cli/__init__.py
crabsnack/__init__.py
crabsnack/__version__.py
crabsnack/text.py