Metadata-Version: 1.1
Name: Crabsnack
Version: 0.1.2
Summary: The best sea food in the world
Home-page: http://github.com/victorziv/crabsnack
Author: Eugene H. Krabs
Author-email: mrkrabs@bottom.com
License: MIT
Platform: UNKNOWN
Classifier: Programming Language :: Python :: 3.3
Classifier: Programming Language :: Python :: 3.4
Classifier: Programming Language :: Python :: 3.5
Classifier: Programming Language :: Python :: 3.6
